finman/__init__.py
finman/__main__.py
finman/app.py
finman/cli/__init__.py
finman/cli/add.py
finman/cli/balance.py
finman/cli/cli_config.py
finman/cli/delete.py
finman/cli/edit.py
finman/cli/list_.py
finman/config/__init__.py
finman/config/config.json
finman/config/config.py
finman/models/__init__.py
finman/models/enums.py
finman/models/record.py
finman/models/wallet.py
finman/utils/__init__.py
finman/utils/cli_utils.py
finman/utils/config_utils.py
finman/utils/data_utils.py
finman/utils/formatter.py
finman/utils/model_utils.py
finman/utils/utils.py
finman-0.1.2.dist-info/LICENSE
finman-0.1.2.dist-info/METADATA
finman-0.1.2.dist-info/WHEEL
finman-0.1.2.dist-info/entry_points.txt
finman-0.1.2.dist-info/RECORD
