Metadata-Version: 2.1
Name: finman
Version: 0.1.2
Summary: Personal Finance Managing CLI Application
License: MIT
Author: Idris Taha
Author-email: dri.taha24@gmail.com
Requires-Python: >=3.10,<4.0
Classifier: License :: OSI Approved :: MIT License
Classifier: Programming Language :: Python :: 3
Classifier: Programming Language :: Python :: 3.10
Classifier: Programming Language :: Python :: 3.11
Classifier: Programming Language :: Python :: 3.12
Requires-Dist: art (>=6.2,<7.0)
Requires-Dist: click (>=8.1.7,<9.0.0)
Requires-Dist: rich (>=13.7.1,<14.0.0)
Requires-Dist: tabulate (>=0.9.0,<0.10.0)
